pkglts/__init__.py
pkglts/config.py
pkglts/config_management.py
pkglts/dependency.py
pkglts/file_management.py
pkglts/hash_management.py
pkglts/local.py
pkglts/logging_tools.py
pkglts/manage.py
pkglts/manage_script.py
pkglts/manage_tools.py
pkglts/option_object.py
pkglts/option_tools.py
pkglts/small_tools.py
pkglts/templating.py
pkglts/tree_ascii_fmt.py
pkglts/version.py
pkglts/version_management.py
pkglts/option/__init__.py
pkglts/option/regenerate.no
pkglts/option/appveyor/__init__.py
pkglts/option/appveyor/option.py
pkglts/option/appveyor/resource/appveyor.yml
pkglts/option/base/__init__.py
pkglts/option/base/option.py
pkglts/option/conda/__init__.py
pkglts/option/conda/option.py
pkglts/option/conda/resource/conda/meta.yaml
pkglts/option/conda/resource/conda/requirements.yml
pkglts/option/conda/resource/conda/requirements_minimal.yml
pkglts/option/conda_alias/__init__.py
pkglts/option/conda_alias/option.py
pkglts/option/conda_alias/resource/conda_alias/meta.yaml
pkglts/option/coverage/__init__.py
pkglts/option/coverage/option.py
pkglts/option/coverage/resource/.coveragerc
pkglts/option/coveralls/__init__.py
pkglts/option/coveralls/option.py
pkglts/option/data/__init__.py
pkglts/option/data/option.py
pkglts/option/data/example/src/{% if data.use_ext_dir %}{{ base.pkgname }}_data{% endif %}/ext_data.png
pkglts/option/data/example/src/{% if data.use_ext_dir %}{{ base.pkgname }}_data{% endif %}/ext_data.txt
pkglts/option/data/example/src/{% if data.use_ext_dir %}{{ base.pkgname }}_data{% endif %}/ext_data.ui
pkglts/option/data/example/src/{% if data.use_ext_dir %}{{ base.pkgname }}_data{% endif %}/sub/sub_ext_data.png
pkglts/option/data/example/src/{% if data.use_ext_dir %}{{ base.pkgname }}_data{% endif %}/sub/sub_ext_data.txt
pkglts/option/data/example/src/{% if data.use_ext_dir %}{{ base.pkgname }}_data{% endif %}/sub/sub_ext_data.ui
pkglts/option/data/example/src/{% if not data.use_ext_dir %}{{ base.pkgname }}{% endif %}/data.png
pkglts-7.10.1.dist-info/AUTHORS.rst
pkglts-7.10.1.dist-info/LICENSE
pkglts-7.10.1.dist-info/METADATA
pkglts-7.10.1.dist-info/WHEEL
pkglts-7.10.1.dist-info/entry_points.txt
pkglts-7.10.1.dist-info/top_level.txt
pkglts-7.10.1.dist-info/RECORD
