Metadata-Version: 2.2
Name: pkglts
Version: 7.10.1
Summary: Building packages with long term support
Author-email: revesansparole <revesansparole@gmail.com>
Maintainer-email: revesansparole <revesansparole@gmail.com>, ThT12 <ThT12@ThT12.fr>, pradal <christophe.pradal@inria.fr>, egarciaitk <emilien.garcia@itk.fr>, Simon Artzet <simon.artzet@gmail.com>, lquibel <lucie.quibel@itk.fr>, Samuel Andres <samuelandres@yandex.com>, Christophe Pradal <christophe.pradal@inria.fr>, Samuel Andres <samuel.andres@itk.fr>
License: CeCILL-C
Project-URL: repository, https://github.com/revesansparole/pkglts
Project-URL: appveyor, https://ci.appveyor.com/project/revesansparole/pkglts/branch/master
Project-URL: coveralls, https://coveralls.io/github/revesansparole/pkglts?branch=master
Project-URL: landscape, https://landscape.io/github/revesansparole/pkglts/master
Project-URL: lgtm, https://lgtm.com/projects/g/revesansparole/pkglts/context:python
Project-URL: pypi, https://badge.fury.io/py/pkglts
Project-URL: readthedocs, https://pkglts.readthedocs.io/en/latest/?badge=latest
Project-URL: requires, https://requires.io/github/revesansparole/pkglts/requirements/?branch=master
Project-URL: travis, https://travis-ci.com/github/revesansparole/pkglts
Keywords: packaging,package builder
Classifier: Development Status :: 2 - Pre-Alpha
Classifier: Intended Audience :: Developers
Classifier: License :: OSI Approved :: BSD License
Classifier: Natural Language :: English
Classifier: Programming Language :: Python
Classifier: Programming Language :: Python :: 3
Classifier: Programming Language :: Python :: 3 :: Only
Classifier: Programming Language :: Python :: 3.10
Classifier: Programming Language :: Python :: 3.11
Classifier: Programming Language :: Python :: 3.6
Classifier: Programming Language :: Python :: 3.7
Classifier: Programming Language :: Python :: 3.8
Classifier: Programming Language :: Python :: 3.9
Requires-Python: >=3.6
License-File: LICENSE
License-File: AUTHORS.rst
Requires-Dist: jinja2
Requires-Dist: requests
Requires-Dist: semver
Requires-Dist: unidecode
Requires-Dist: url-normalize
Provides-Extra: doc
Requires-Dist: sphinx; extra == "doc"
Requires-Dist: sphinx-rtd-theme; extra == "doc"
Provides-Extra: dvlpt
Requires-Dist: flake8; extra == "dvlpt"
Requires-Dist: twine; extra == "dvlpt"
Provides-Extra: test
Requires-Dist: coverage; extra == "test"
Requires-Dist: coveralls; extra == "test"
Requires-Dist: pytest; extra == "test"
Requires-Dist: pytest-cov; extra == "test"
Requires-Dist: pytest-mock; extra == "test"
Requires-Dist: tox; extra == "test"
